README.rst
setup.py
cyglfw3/__init__.py
cyglfw3/cglfw3.pxd
cyglfw3/compatible.py
cyglfw3/glfw3.c
cyglfw3/glfw3.pyx
cyglfw3/version.py
cyglfw3.egg-info/PKG-INFO
cyglfw3.egg-info/SOURCES.txt
cyglfw3.egg-info/dependency_links.txt
cyglfw3.egg-info/requires.txt
cyglfw3.egg-info/top_level.txt