Metadata-Version: 1.1
Name: cyglfw3
Version: 3.0.4.7
Summary: Python bindings for GLFW 3+ using Cython
Home-page: http://github.com/adamlwgriffiths/cyglfw3
Author: Adam Griffiths
Author-email: adam.lw.griffiths@gmail.com
License: BSD
Platform: any
Classifier: Development Status :: 4 - Beta
Classifier: Natural Language :: English
Classifier: Intended Audience :: Developers
Classifier: Operating System :: MacOS :: MacOS X
Classifier: Operating System :: Microsoft :: Windows
Classifier: Operating System :: POSIX
Classifier: Programming Language :: Python
Classifier: Topic :: Multimedia :: Graphics
Classifier: Topic :: Multimedia :: Graphics :: 3D Rendering
Classifier: License :: OSI Approved :: BSD License
Classifier: Topic :: Software Development :: Libraries
Classifier: Topic :: Software Development :: Libraries :: Python Modules
Requires: cython
